[
    {
        "rakam": 1,
        "ayah": "قُلْ يَا أَيُّهَا الْكَافِرُونَ",
        "content": ""
    },
    {
        "rakam": 2,
        "ayah": "لَا أَعْبُدُ مَا تَعْبُدُونَ",
        "content": ""
    },
    {
        "rakam": 3,
        "ayah": "وَلَا أَنتُمْ عَابِدُونَ مَا أَعْبُدُ",
        "content": ""
    },
    {
        "rakam": 4,
        "ayah": "وَلَا أَنَا عَابِدٌ مَّا عَبَدتُّمْ",
        "content": ""
    },
    {
        "rakam": 5,
        "ayah": "وَلَا أَنتُمْ عَابِدُونَ مَا أَعْبُدُ",
        "content": ""
    },
    {
        "rakam": 6,
        "ayah": "لَكُمْ دِينُكُمْ وَلِيَ دِينِ",
        "content": ""
    }
]